MANIFEST.in
setup.py
pepperedform/__init__.py
pepperedform/handler.py
pepperedform/render.py
pepperedform/renderutils.py
pepperedform.egg-info/PKG-INFO
pepperedform.egg-info/SOURCES.txt
pepperedform.egg-info/dependency_links.txt
pepperedform.egg-info/not-zip-safe
pepperedform.egg-info/requires.txt
pepperedform.egg-info/top_level.txt
pepperedform/static/js/repeater.js
pepperedform/tests/__init__.py
pepperedform/tests/test_handler.py
pepperedform/tests/test_render.py
pepperedform/tests/test_renderutils.py