Metadata-Version: 1.0
Name: pepperedform
Version: 0.4.6
Summary: Helpers for using peppercorn with formprocess.
Home-page: UNKNOWN
Author: Ian Wilson
Author-email: ian@laspilitas.com
License: BSD
Platform: UNKNOWN
Classifier: Development Status :: 3 - Alpha
Classifier: Topic :: Utilities
Classifier: License :: OSI Approved :: BSD License
